scrapy_prometheus_extensions/__init__.py
scrapy_prometheus_extensions/scrapy_prometheus_push.py
scrapy_prometheus_extensions-1.2.5.dist-info/LICENSE
scrapy_prometheus_extensions-1.2.5.dist-info/METADATA
scrapy_prometheus_extensions-1.2.5.dist-info/WHEEL
scrapy_prometheus_extensions-1.2.5.dist-info/top_level.txt
scrapy_prometheus_extensions-1.2.5.dist-info/RECORD
