Metadata-Version: 2.1
Name: scrapy-prometheus-extensions
Version: 1.2.5
Summary: scrapy_prometheus_extensions
Home-page: https://github.com/boyLong/scrapy-prometheus-extensions
Author: wenlong_gao
Author-email: g1310669621@gmail.com
Project-URL: Bug Tracker, https://github.com/boyLong/scrapy-prometheus-extensions/issues
Classifier: Programming Language :: Python :: 3
Classifier: License :: OSI Approved :: MIT License
Classifier: Operating System :: OS Independent
Requires-Python: >=3.6
License-File: LICENSE
